macapi/__init__.py
macapi/api_base.py
macapi/version.py
macapi/alerts/__init__.py
macapi/alerts/alerts.py
macapi/cluster/__init__.py
macapi/cluster/cluster.py
macapi/ip_whitelist/__init__.py
macapi/ip_whitelist/ip_whitelist.py
macapi/ipwhitelist/__init__.py
macapi/ipwhitelist/ipwhitelist.py
macapi-1.0.5.dist-info/LICENSE.md
macapi-1.0.5.dist-info/METADATA
macapi-1.0.5.dist-info/WHEEL
macapi-1.0.5.dist-info/entry_points.txt
macapi-1.0.5.dist-info/top_level.txt
macapi-1.0.5.dist-info/RECORD
