Metadata-Version: 2.1
Name: macapi
Version: 1.0.5
Summary: scripts written to interact with mongodb cloud api
Home-page: https://github.com/dmcna005/macapi
Author: Dwayne McNab
Author-email: dmcnab@imperiadata.com
License: Apache 2.0
Platform: UNKNOWN
Classifier: Development Status :: 5 - Production/Stable
Classifier: License :: OSI Approved :: Apache Software License
Classifier: Programming Language :: Python :: 2.7
Classifier: Topic :: Database :: Database Engines/Servers
Classifier: Intended Audience :: Developers
Requires-Dist: requests
